dp_sample_summary/__init__.py
dp_sample_summary/result/__init__.py
dp_sample_summary/result/frontend/build/asset-manifest.json
dp_sample_summary/result/frontend/build/index.html
dp_sample_summary/result/frontend/build/static/css/main.4315ee16.css
dp_sample_summary/result/frontend/build/static/css/main.4315ee16.css.map
dp_sample_summary/result/frontend/build/static/js/main.2a5f7864.js
dp_sample_summary/result/frontend/build/static/js/main.2a5f7864.js.LICENSE.txt
dp_sample_summary/result/frontend/build/static/js/main.2a5f7864.js.map
dp_sample_summary/search/__init__.py
dp_sample_summary/search/frontend/build/asset-manifest.json
dp_sample_summary/search/frontend/build/index.html
dp_sample_summary/search/frontend/build/static/css/main.ee3f2597.css
dp_sample_summary/search/frontend/build/static/css/main.ee3f2597.css.map
dp_sample_summary/search/frontend/build/static/js/main.c5e178e8.js
dp_sample_summary/search/frontend/build/static/js/main.c5e178e8.js.LICENSE.txt
dp_sample_summary/search/frontend/build/static/js/main.c5e178e8.js.map
dp_sample_summary-0.0.4.dist-info/LICENSE
dp_sample_summary-0.0.4.dist-info/METADATA
dp_sample_summary-0.0.4.dist-info/WHEEL
dp_sample_summary-0.0.4.dist-info/top_level.txt
dp_sample_summary-0.0.4.dist-info/RECORD
