Metadata-Version: 2.1
Name: dp-sample-summary
Version: 0.0.4
Home-page: 
Author: 
Author-email: 
Requires-Python: >=3.6
License-File: LICENSE
Requires-Dist: streamlit >=0.63
